kdtrees/__init__.py
kdtrees/_kdtree.py
kdtrees/_kdtree_type.py
kdtrees/_utils.py
kdtrees/kdtree_type.py
tests/__init__.py
tests/test_fixtures.py
tests/test_kdtree.py
tests/test_kdtree_delete.py
tests/test_kdtree_init.py
tests/test_kdtree_insert.py
tests/test_kdtree_neighbors.py
tests/test_kdtree_search.py
tests/test_kdtree_type.py
tests/test_utils.py
tests/test_utils_check_dim.py
tests/test_utils_distance.py
tests/test_utils_format_array.py
kdtrees-0.1.7.dist-info/LICENSE
kdtrees-0.1.7.dist-info/METADATA
kdtrees-0.1.7.dist-info/WHEEL
kdtrees-0.1.7.dist-info/top_level.txt
kdtrees-0.1.7.dist-info/zip-safe
kdtrees-0.1.7.dist-info/RECORD
