Metadata-Version: 2.1
Name: kdtrees
Version: 0.1.7
Summary: Python implementation of a K-D Tree as a pseudo-balanced Tree
Home-page: http://github.com/paradoxysm/kdtrees
Author: paradoxysm
Author-email: paradoxysm.dev@gmail.com
License: BSD-3-Clause
Download-URL: https://github.com/paradoxysm/kdtrees/archive/0.1.7.tar.gz
Keywords: kdtree,python,data-structures
Platform: UNKNOWN
Classifier: Development Status :: 4 - Beta
Classifier: Intended Audience :: Developers
Classifier: Natural Language :: English
Classifier: License :: OSI Approved :: BSD License
Classifier: Operating System :: OS Independent
Classifier: Programming Language :: Python
Classifier: Programming Language :: Python :: 3
Classifier: Programming Language :: Python :: 3.4
Classifier: Programming Language :: Python :: 3.5
Classifier: Programming Language :: Python :: 3.6
Classifier: Programming Language :: Python :: 3.7
Classifier: Topic :: Software Development :: Libraries
Classifier: Topic :: Utilities
Requires-Python: >=3.4, <4
Requires-Dist: numpy
Provides-Extra: test
Requires-Dist: pytest ; extra == 'test'
Requires-Dist: coverage ; extra == 'test'
Requires-Dist: pytest-cov ; extra == 'test'
